{"window":{"start":"2019-05-03T07:17:40.000+09:00","end":"2019-05-03T07:17:45.000+09:00"},"GID_INDEX":"758ade6d5aa16b04a0e63dc336f73b45_10.0","SEXNUM_":2,"G_SEXNUM":2,"CITYCODE_":41,"G_CITYCODE":41,"AGECODE_":6,"G_AGECODE":6,"G_BLOODSUGAR_AVG":85.33333333333333,"G_BLOODSUGAR_DSTD":0.5773502691896257,"G_SBP_AVG":112.66666666666667,"G_SBP_DSTD":6.6583281184793925,"G_DBP_AVG":69.0,"G_DBP_DSTD":7.937253933193772,"G_DRINK_CNCT":"1/0/0","G_DRINK_DMX":1,"G_CIGAR_CNCT":"1/1/1","G_CIGAR_DMX":1,"G_SEX_CNCT":"female/female/female","G_SEX_DMX":"female","GID_INDEX":"758ade6d5aa16b04a0e63dc336f73b45_10.0"}
{"window":{"start":"2019-05-03T07:17:40.000+09:00","end":"2019-05-03T07:17:45.000+09:00"},"GID_INDEX":"690d6ba68aac65b5a571c4be19833338_1.0","SEXNUM_":2,"G_SEXNUM":2,"CITYCODE_":47,"G_CITYCODE":47,"AGECODE_":14,"G_AGECODE":14,"G_BLOODSUGAR_AVG":89.33333333333333,"G_BLOODSUGAR_DSTD":1.1547005383792515,"G_SBP_AVG":116.66666666666667,"G_SBP_DSTD":5.773502691896258,"G_DBP_AVG":76.66666666666667,"G_DBP_DSTD":5.773502691896258,"G_DRINK_CNCT":"1/1/1","G_DRINK_DMX":1,"G_CIGAR_CNCT":"1/1/1","G_CIGAR_DMX":1,"G_SEX_CNCT":"female/female/female","G_SEX_DMX":"female","GID_INDEX":"690d6ba68aac65b5a571c4be19833338_1.0"}
{"window":{"start":"2019-05-03T07:17:40.000+09:00","end":"2019-05-03T07:17:45.000+09:00"},"GID_INDEX":"b8a2f63b4936b1b4d2951ce8cb80db24_6.0","SEXNUM_":2,"G_SEXNUM":2,"CITYCODE_":45,"G_CITYCODE":45,"AGECODE_":13,"G_AGECODE":13,"G_BLOODSUGAR_AVG":109.0,"G_BLOODSUGAR_DSTD":6.082762530298219,"G_SBP_AVG":129.66666666666666,"G_SBP_DSTD":17.7857620959388,"G_DBP_AVG":79.33333333333333,"G_DBP_DSTD":10.066445913694334,"G_DRINK_CNCT":"1/1/1","G_DRINK_DMX":1,"G_CIGAR_CNCT":"1/1/3","G_CIGAR_DMX":3,"G_SEX_CNCT":"female/female/female","G_SEX_DMX":"female","GID_INDEX":"b8a2f63b4936b1b4d2951ce8cb80db24_6.0"}
{"window":{"start":"2019-05-03T07:17:40.000+09:00","end":"2019-05-03T07:17:45.000+09:00"},"GID_INDEX":"beaca58d15f70403b216025c6f545c89_8.0","SEXNUM_":2,"G_SEXNUM":2,"CITYCODE_":42,"G_CITYCODE":42,"AGECODE_":11,"G_AGECODE":11,"G_BLOODSUGAR_AVG":144.0,"G_BLOODSUGAR_DSTD":20.663978319771825,"G_SBP_AVG":154.33333333333334,"G_SBP_DSTD":40.079088479322145,"G_DBP_AVG":80.0,"G_DBP_DSTD":10.0,"G_DRINK_CNCT":"1/0/1","G_DRINK_DMX":1,"G_CIGAR_CNCT":"1/1/1","G_CIGAR_DMX":1,"G_SEX_CNCT":"female/female/female","G_SEX_DMX":"female","GID_INDEX":"beaca58d15f70403b216025c6f545c89_8.0"}
{"window":{"start":"2019-05-03T07:17:40.000+09:00","end":"2019-05-03T07:17:45.000+09:00"},"GID_INDEX":"b9226206c007174117d4a2de4ea3b67d_6.0","SEXNUM_":2,"G_SEXNUM":2,"CITYCODE_":46,"G_CITYCODE":46,"AGECODE_":10,"G_AGECODE":10,"G_BLOODSUGAR_AVG":101.0,"G_BLOODSUGAR_DSTD":1.0,"G_SBP_AVG":117.33333333333333,"G_SBP_DSTD":23.692474191889147,"G_DBP_AVG":74.66666666666667,"G_DBP_DSTD":12.858201014657274,"G_DRINK_CNCT":"1/0/1","G_DRINK_DMX":1,"G_CIGAR_CNCT":"3/3/1","G_CIGAR_DMX":3,"G_SEX_CNCT":"female/female/female","G_SEX_DMX":"female","GID_INDEX":"b9226206c007174117d4a2de4ea3b67d_6.0"}
{"window":{"start":"2019-05-03T07:17:40.000+09:00","end":"2019-05-03T07:17:45.000+09:00"},"GID_INDEX":"1bae87047774bd4631ea1e860fe4254c_6.0","SEXNUM_":1,"G_SEXNUM":1,"CITYCODE_":26,"G_CITYCODE":26,"AGECODE_":12,"G_AGECODE":12,"G_BLOODSUGAR_AVG":109.0,"G_BLOODSUGAR_DSTD":1.0,"G_SBP_AVG":118.0,"G_SBP_DSTD":11.135528725660043,"G_DBP_AVG":80.66666666666667,"G_DBP_DSTD":10.263202878893768,"G_DRINK_CNCT":"1/0/0","G_DRINK_DMX":1,"G_CIGAR_CNCT":"3/3/3","G_CIGAR_DMX":3,"G_SEX_CNCT":"male/male/male","G_SEX_DMX":"male","GID_INDEX":"1bae87047774bd4631ea1e860fe4254c_6.0"}
{"window":{"start":"2019-05-03T07:17:40.000+09:00","end":"2019-05-03T07:17:45.000+09:00"},"GID_INDEX":"cc17de76aecdc722dbe1a83fdef92084_9.0","SEXNUM_":2,"G_SEXNUM":2,"CITYCODE_":27,"G_CITYCODE":27,"AGECODE_":11,"G_AGECODE":11,"G_BLOODSUGAR_AVG":95.0,"G_BLOODSUGAR_DSTD":0.0,"G_SBP_AVG":137.0,"G_SBP_DSTD":21.517434791350013,"G_DBP_AVG":80.33333333333333,"G_DBP_DSTD":9.60902353693305,"G_DRINK_CNCT":"0/0/1","G_DRINK_DMX":1,"G_CIGAR_CNCT":"1/1/1","G_CIGAR_DMX":1,"G_SEX_CNCT":"female/female/female","G_SEX_DMX":"female","GID_INDEX":"cc17de76aecdc722dbe1a83fdef92084_9.0"}
{"window":{"start":"2019-05-03T07:17:40.000+09:00","end":"2019-05-03T07:17:45.000+09:00"},"GID_INDEX":"3fe833700922f86b4cc7f86af7413b67_1.0","SEXNUM_":1,"G_SEXNUM":1,"CITYCODE_":11,"G_CITYCODE":11,"AGECODE_":10,"G_AGECODE":10,"G_BLOODSUGAR_AVG":75.66666666666667,"G_BLOODSUGAR_DSTD":2.081665999466133,"G_SBP_AVG":112.33333333333333,"G_SBP_DSTD":9.291573243177568,"G_DBP_AVG":78.33333333333333,"G_DBP_DSTD":2.0816659994661326,"G_DRINK_CNCT":"0/1/1","G_DRINK_DMX":1,"G_CIGAR_CNCT":"3/1/3","G_CIGAR_DMX":3,"G_SEX_CNCT":"male/male/male","G_SEX_DMX":"male","GID_INDEX":"3fe833700922f86b4cc7f86af7413b67_1.0"}
{"window":{"start":"2019-05-03T07:17:40.000+09:00","end":"2019-05-03T07:17:45.000+09:00"},"GID_INDEX":"82abcd0743c4117ddc44056cae8d770a_2.0","SEXNUM_":2,"G_SEXNUM":2,"CITYCODE_":29,"G_CITYCODE":29,"AGECODE_":12,"G_AGECODE":12,"G_BLOODSUGAR_AVG":97.66666666666667,"G_BLOODSUGAR_DSTD":4.041451884327381,"G_SBP_AVG":122.33333333333333,"G_SBP_DSTD":5.8594652770823155,"G_DBP_AVG":74.66666666666667,"G_DBP_DSTD":5.033222956847166,"G_DRINK_CNCT":"1/1/1","G_DRINK_DMX":1,"G_CIGAR_CNCT":"1/1/1","G_CIGAR_DMX":1,"G_SEX_CNCT":"female/female/female","G_SEX_DMX":"female","GID_INDEX":"82abcd0743c4117ddc44056cae8d770a_2.0"}
{"window":{"start":"2019-05-03T07:17:40.000+09:00","end":"2019-05-03T07:17:45.000+09:00"},"GID_INDEX":"a034bcab6a299818d0961f30f85848c4_1.0","SEXNUM_":2,"G_SEXNUM":2,"CITYCODE_":48,"G_CITYCODE":48,"AGECODE_":9,"G_AGECODE":9,"G_BLOODSUGAR_AVG":78.0,"G_BLOODSUGAR_DSTD":2.0,"G_SBP_AVG":107.66666666666667,"G_SBP_DSTD":4.041451884327381,"G_DBP_AVG":70.0,"G_DBP_DSTD":9.0,"G_DRINK_CNCT":"1/0/1","G_DRINK_DMX":1,"G_CIGAR_CNCT":"3/1/1","G_CIGAR_DMX":3,"G_SEX_CNCT":"female/female/female","G_SEX_DMX":"female","GID_INDEX":"a034bcab6a299818d0961f30f85848c4_1.0"}
{"window":{"start":"2019-05-03T07:17:40.000+09:00","end":"2019-05-03T07:17:45.000+09:00"},"GID_INDEX":"ed61ce13f2f96cf6694c5c1063e5b465_1.0","SEXNUM_":2,"G_SEXNUM":2,"CITYCODE_":43,"G_CITYCODE":43,"AGECODE_":9,"G_AGECODE":9,"G_BLOODSUGAR_AVG":77.66666666666667,"G_BLOODSUGAR_DSTD":3.5118845842842465,"G_SBP_AVG":121.66666666666667,"G_SBP_DSTD":12.583057392117917,"G_DBP_AVG":76.0,"G_DBP_DSTD":7.937253933193772,"G_DRINK_CNCT":"0/0/1","G_DRINK_DMX":1,"G_CIGAR_CNCT":"2/1/1","G_CIGAR_DMX":2,"G_SEX_CNCT":"female/female/female","G_SEX_DMX":"female","GID_INDEX":"ed61ce13f2f96cf6694c5c1063e5b465_1.0"}
