{"window":{"start":"2019-05-03T07:20:45.000+09:00","end":"2019-05-03T07:20:50.000+09:00"},"GID_INDEX":"c887cb98840ee6cf0012f218fa65ef46_7.0","SEXNUM_":1,"G_SEXNUM":1,"CITYCODE_":47,"G_CITYCODE":47,"AGECODE_":12,"G_AGECODE":12,"G_BLOODSUGAR_AVG":214.0,"G_BLOODSUGAR_DSTD":84.1843215806839,"G_SBP_AVG":139.0,"G_SBP_DSTD":10.14889156509222,"G_DBP_AVG":83.0,"G_DBP_DSTD":6.082762530298219,"G_DRINK_CNCT":"0/0/0","G_DRINK_DMX":0,"G_CIGAR_CNCT":"3/3/3","G_CIGAR_DMX":3,"G_SEX_CNCT":"male/male/male","G_SEX_DMX":"male","GID_INDEX":"c887cb98840ee6cf0012f218fa65ef46_7.0"}
