{"window":{"start":"2019-05-03T07:17:40.000+09:00","end":"2019-05-03T07:17:45.000+09:00"},"GID_INDEX":"16f1b924adf23d0646426ecf444b9073_1.0","SEXNUM_":2,"G_SEXNUM":2,"CITYCODE_":27,"G_CITYCODE":27,"AGECODE_":5,"G_AGECODE":5,"G_BLOODSUGAR_AVG":73.0,"G_BLOODSUGAR_DSTD":1.0,"G_SBP_AVG":106.66666666666667,"G_SBP_DSTD":5.773502691896258,"G_DBP_AVG":66.66666666666667,"G_DBP_DSTD":5.773502691896258,"G_DRINK_CNCT":"1/0/0","G_DRINK_DMX":1,"G_CIGAR_CNCT":"3/1/1","G_CIGAR_DMX":3,"G_SEX_CNCT":"female/female/female","G_SEX_DMX":"female","GID_INDEX":"16f1b924adf23d0646426ecf444b9073_1.0"}
{"window":{"start":"2019-05-03T07:17:40.000+09:00","end":"2019-05-03T07:17:45.000+09:00"},"GID_INDEX":"ec92c587108cc2ced622956a71c2b285_1.0","SEXNUM_":2,"G_SEXNUM":2,"CITYCODE_":30,"G_CITYCODE":30,"AGECODE_":10,"G_AGECODE":10,"G_BLOODSUGAR_AVG":87.0,"G_BLOODSUGAR_DSTD":1.0,"G_SBP_AVG":106.66666666666667,"G_SBP_DSTD":11.547005383792516,"G_DBP_AVG":70.0,"G_DBP_DSTD":10.0,"G_DRINK_CNCT":"1/0/0","G_DRINK_DMX":1,"G_CIGAR_CNCT":"3/1/1","G_CIGAR_DMX":3,"G_SEX_CNCT":"female/female/female","G_SEX_DMX":"female","GID_INDEX":"ec92c587108cc2ced622956a71c2b285_1.0"}
{"window":{"start":"2019-05-03T07:17:40.000+09:00","end":"2019-05-03T07:17:45.000+09:00"},"GID_INDEX":"3544b757ac48756558e9f2182a916158_4.0","SEXNUM_":2,"G_SEXNUM":2,"CITYCODE_":45,"G_CITYCODE":45,"AGECODE_":11,"G_AGECODE":11,"G_BLOODSUGAR_AVG":89.0,"G_BLOODSUGAR_DSTD":1.0,"G_SBP_AVG":121.0,"G_SBP_DSTD":20.074859899884732,"G_DBP_AVG":75.0,"G_DBP_DSTD":12.288205727444508,"G_DRINK_CNCT":"1/1/1","G_DRINK_DMX":1,"G_CIGAR_CNCT":"1/1/1","G_CIGAR_DMX":1,"G_SEX_CNCT":"female/female/female","G_SEX_DMX":"female","GID_INDEX":"3544b757ac48756558e9f2182a916158_4.0"}
{"window":{"start":"2019-05-03T07:17:40.000+09:00","end":"2019-05-03T07:17:45.000+09:00"},"GID_INDEX":"cc23c3a380537d0b847f6b102553f779_6.0","SEXNUM_":2,"G_SEXNUM":2,"CITYCODE_":29,"G_CITYCODE":29,"AGECODE_":9,"G_AGECODE":9,"G_BLOODSUGAR_AVG":102.0,"G_BLOODSUGAR_DSTD":2.6457513110645907,"G_SBP_AVG":120.0,"G_SBP_DSTD":17.320508075688775,"G_DBP_AVG":76.66666666666667,"G_DBP_DSTD":5.773502691896258,"G_DRINK_CNCT":"1/1/1","G_DRINK_DMX":1,"G_CIGAR_CNCT":"1/1/1","G_CIGAR_DMX":1,"G_SEX_CNCT":"female/female/female","G_SEX_DMX":"female","GID_INDEX":"cc23c3a380537d0b847f6b102553f779_6.0"}
{"window":{"start":"2019-05-03T07:17:40.000+09:00","end":"2019-05-03T07:17:45.000+09:00"},"GID_INDEX":"ed9b6edc4197807592c46a357c6a22db_15.0","SEXNUM_":2,"G_SEXNUM":2,"CITYCODE_":47,"G_CITYCODE":47,"AGECODE_":11,"G_AGECODE":11,"G_BLOODSUGAR_AVG":190.0,"G_BLOODSUGAR_DSTD":14.798648586948742,"G_SBP_AVG":128.66666666666666,"G_SBP_DSTD":2.309401076758503,"G_DBP_AVG":78.0,"G_DBP_DSTD":3.4641016151377544,"G_DRINK_CNCT":"1/1/0","G_DRINK_DMX":1,"G_CIGAR_CNCT":"1/1/1","G_CIGAR_DMX":1,"G_SEX_CNCT":"female/female/female","G_SEX_DMX":"female","GID_INDEX":"ed9b6edc4197807592c46a357c6a22db_15.0"}
{"window":{"start":"2019-05-03T07:17:40.000+09:00","end":"2019-05-03T07:17:45.000+09:00"},"GID_INDEX":"2fc60bcca438b6d7ca2d243a5c65dfe9_24.0","SEXNUM_":1,"G_SEXNUM":1,"CITYCODE_":41,"G_CITYCODE":41,"AGECODE_":13,"G_AGECODE":13,"G_BLOODSUGAR_AVG":259.3333333333333,"G_BLOODSUGAR_DSTD":28.219378684395824,"G_SBP_AVG":131.66666666666666,"G_SBP_DSTD":10.969655114602888,"G_DBP_AVG":76.33333333333333,"G_DBP_DSTD":11.930353445448853,"G_DRINK_CNCT":"1/0/0","G_DRINK_DMX":1,"G_CIGAR_CNCT":"3/3/3","G_CIGAR_DMX":3,"G_SEX_CNCT":"male/male/male","G_SEX_DMX":"male","GID_INDEX":"2fc60bcca438b6d7ca2d243a5c65dfe9_24.0"}
{"window":{"start":"2019-05-03T07:17:40.000+09:00","end":"2019-05-03T07:17:45.000+09:00"},"GID_INDEX":"7aab9a7e1f7857a25a4b10e5ed60ef1b_11.0","SEXNUM_":2,"G_SEXNUM":2,"CITYCODE_":29,"G_CITYCODE":29,"AGECODE_":11,"G_AGECODE":11,"G_BLOODSUGAR_AVG":97.66666666666667,"G_BLOODSUGAR_DSTD":0.5773502691896257,"G_SBP_AVG":114.66666666666667,"G_SBP_DSTD":10.066445913694333,"G_DBP_AVG":74.0,"G_DBP_DSTD":5.5677643628300215,"G_DRINK_CNCT":"1/0/1","G_DRINK_DMX":1,"G_CIGAR_CNCT":"1/2/1","G_CIGAR_DMX":2,"G_SEX_CNCT":"female/female/female","G_SEX_DMX":"female","GID_INDEX":"7aab9a7e1f7857a25a4b10e5ed60ef1b_11.0"}
{"window":{"start":"2019-05-03T07:17:40.000+09:00","end":"2019-05-03T07:17:45.000+09:00"},"GID_INDEX":"2f8dffa089928d0b66f788e84ecdc0ec_2.0","SEXNUM_":2,"G_SEXNUM":2,"CITYCODE_":27,"G_CITYCODE":27,"AGECODE_":15,"G_AGECODE":15,"G_BLOODSUGAR_AVG":134.66666666666666,"G_BLOODSUGAR_DSTD":14.571661996262929,"G_SBP_AVG":127.66666666666667,"G_SBP_DSTD":8.736894948054104,"G_DBP_AVG":78.0,"G_DBP_DSTD":12.0,"G_DRINK_CNCT":"1/1/1","G_DRINK_DMX":1,"G_CIGAR_CNCT":"1/1/1","G_CIGAR_DMX":1,"G_SEX_CNCT":"female/female/female","G_SEX_DMX":"female","GID_INDEX":"2f8dffa089928d0b66f788e84ecdc0ec_2.0"}
{"window":{"start":"2019-05-03T07:17:40.000+09:00","end":"2019-05-03T07:17:45.000+09:00"},"GID_INDEX":"38b17deab8d58b7f86191d261729c11a_7.0","SEXNUM_":2,"G_SEXNUM":2,"CITYCODE_":26,"G_CITYCODE":26,"AGECODE_":13,"G_AGECODE":13,"G_BLOODSUGAR_AVG":99.66666666666667,"G_BLOODSUGAR_DSTD":1.5275252316519468,"G_SBP_AVG":119.0,"G_SBP_DSTD":9.0,"G_DBP_AVG":70.33333333333333,"G_DBP_DSTD":3.511884584284246,"G_DRINK_CNCT":"1/1/1","G_DRINK_DMX":1,"G_CIGAR_CNCT":"1/1/1","G_CIGAR_DMX":1,"G_SEX_CNCT":"female/female/female","G_SEX_DMX":"female","GID_INDEX":"38b17deab8d58b7f86191d261729c11a_7.0"}
