{"window":{"start":"2019-05-03T07:17:40.000+09:00","end":"2019-05-03T07:17:45.000+09:00"},"GID_INDEX":"dd151e12924ff19fccf665b264602f8d_6.0","SEXNUM_":2,"G_SEXNUM":2,"CITYCODE_":11,"G_CITYCODE":11,"AGECODE_":6,"G_AGECODE":6,"G_BLOODSUGAR_AVG":82.66666666666667,"G_BLOODSUGAR_DSTD":1.5275252316519468,"G_SBP_AVG":102.33333333333333,"G_SBP_DSTD":2.081665999466133,"G_DBP_AVG":63.666666666666664,"G_DBP_DSTD":3.511884584284246,"G_DRINK_CNCT":"1/0/1","G_DRINK_DMX":1,"G_CIGAR_CNCT":"1/1/3","G_CIGAR_DMX":3,"G_SEX_CNCT":"female/female/female","G_SEX_DMX":"female","GID_INDEX":"dd151e12924ff19fccf665b264602f8d_6.0"}
{"window":{"start":"2019-05-03T07:17:40.000+09:00","end":"2019-05-03T07:17:45.000+09:00"},"GID_INDEX":"0d53dd0e743b2172896b2519eba3ef70_5.0","SEXNUM_":1,"G_SEXNUM":1,"CITYCODE_":28,"G_CITYCODE":28,"AGECODE_":12,"G_AGECODE":12,"G_BLOODSUGAR_AVG":98.66666666666667,"G_BLOODSUGAR_DSTD":2.886751345948129,"G_SBP_AVG":116.33333333333333,"G_SBP_DSTD":20.256686138984662,"G_DBP_AVG":72.0,"G_DBP_DSTD":14.422205101855956,"G_DRINK_CNCT":"1/1/0","G_DRINK_DMX":1,"G_CIGAR_CNCT":"1/1/3","G_CIGAR_DMX":3,"G_SEX_CNCT":"male/male/male","G_SEX_DMX":"male","GID_INDEX":"0d53dd0e743b2172896b2519eba3ef70_5.0"}
{"window":{"start":"2019-05-03T07:17:40.000+09:00","end":"2019-05-03T07:17:45.000+09:00"},"GID_INDEX":"b1a62da4b955edf43bf1a422ee1378d0_14.0","SEXNUM_":2,"G_SEXNUM":2,"CITYCODE_":11,"G_CITYCODE":11,"AGECODE_":5,"G_AGECODE":5,"G_BLOODSUGAR_AVG":101.66666666666667,"G_BLOODSUGAR_DSTD":0.5773502691896257,"G_SBP_AVG":117.0,"G_SBP_DSTD":7.0,"G_DBP_AVG":76.0,"G_DBP_DSTD":6.557438524302,"G_DRINK_CNCT":"0/0/0","G_DRINK_DMX":0,"G_CIGAR_CNCT":"1/1/1","G_CIGAR_DMX":1,"G_SEX_CNCT":"female/female/female","G_SEX_DMX":"female","GID_INDEX":"b1a62da4b955edf43bf1a422ee1378d0_14.0"}
{"window":{"start":"2019-05-03T07:17:40.000+09:00","end":"2019-05-03T07:17:45.000+09:00"},"GID_INDEX":"47f10a0af47518bb47643d3eb4e331bc_4.0","SEXNUM_":2,"G_SEXNUM":2,"CITYCODE_":44,"G_CITYCODE":44,"AGECODE_":11,"G_AGECODE":11,"G_BLOODSUGAR_AVG":100.66666666666667,"G_BLOODSUGAR_DSTD":1.5275252316519468,"G_SBP_AVG":127.66666666666667,"G_SBP_DSTD":8.020806277010642,"G_DBP_AVG":82.33333333333333,"G_DBP_DSTD":4.932882862316248,"G_DRINK_CNCT":"1/1/0","G_DRINK_DMX":1,"G_CIGAR_CNCT":"1/1/1","G_CIGAR_DMX":1,"G_SEX_CNCT":"female/female/female","G_SEX_DMX":"female","GID_INDEX":"47f10a0af47518bb47643d3eb4e331bc_4.0"}
{"window":{"start":"2019-05-03T07:17:40.000+09:00","end":"2019-05-03T07:17:45.000+09:00"},"GID_INDEX":"3c61ff67707d1d5ed78ee05d7db7b231_3.0","SEXNUM_":2,"G_SEXNUM":2,"CITYCODE_":47,"G_CITYCODE":47,"AGECODE_":5,"G_AGECODE":5,"G_BLOODSUGAR_AVG":79.0,"G_BLOODSUGAR_DSTD":1.0,"G_SBP_AVG":100.0,"G_SBP_DSTD":10.0,"G_DBP_AVG":63.333333333333336,"G_DBP_DSTD":5.773502691896258,"G_DRINK_CNCT":"0/0/1","G_DRINK_DMX":1,"G_CIGAR_CNCT":"1/1/1","G_CIGAR_DMX":1,"G_SEX_CNCT":"female/female/female","G_SEX_DMX":"female","GID_INDEX":"3c61ff67707d1d5ed78ee05d7db7b231_3.0"}
{"window":{"start":"2019-05-03T07:17:40.000+09:00","end":"2019-05-03T07:17:45.000+09:00"},"GID_INDEX":"ae4a651b5e2c474dae92778013882504_1.0","SEXNUM_":2,"G_SEXNUM":2,"CITYCODE_":11,"G_CITYCODE":11,"AGECODE_":13,"G_AGECODE":13,"G_BLOODSUGAR_AVG":74.33333333333333,"G_BLOODSUGAR_DSTD":3.511884584284246,"G_SBP_AVG":121.33333333333333,"G_SBP_DSTD":11.846237095944574,"G_DBP_AVG":75.66666666666667,"G_DBP_DSTD":3.214550253664318,"G_DRINK_CNCT":"1/1/1","G_DRINK_DMX":1,"G_CIGAR_CNCT":"3/1/1","G_CIGAR_DMX":3,"G_SEX_CNCT":"female/female/female","G_SEX_DMX":"female","GID_INDEX":"ae4a651b5e2c474dae92778013882504_1.0"}
{"window":{"start":"2019-05-03T07:17:40.000+09:00","end":"2019-05-03T07:17:45.000+09:00"},"GID_INDEX":"3b07c67ccd7c9fee6b6cfc458e401df9_4.0","SEXNUM_":1,"G_SEXNUM":1,"CITYCODE_":11,"G_CITYCODE":11,"AGECODE_":5,"G_AGECODE":5,"G_BLOODSUGAR_AVG":89.33333333333333,"G_BLOODSUGAR_DSTD":4.163331998932266,"G_SBP_AVG":128.66666666666666,"G_SBP_DSTD":23.43786110832926,"G_DBP_AVG":75.33333333333333,"G_DBP_DSTD":17.473789896108208,"G_DRINK_CNCT":"1/0/0","G_DRINK_DMX":1,"G_CIGAR_CNCT":"3/1/1","G_CIGAR_DMX":3,"G_SEX_CNCT":"male/male/male","G_SEX_DMX":"male","GID_INDEX":"3b07c67ccd7c9fee6b6cfc458e401df9_4.0"}
{"window":{"start":"2019-05-03T07:17:40.000+09:00","end":"2019-05-03T07:17:45.000+09:00"},"GID_INDEX":"b0674834872f6f7d7eeb893852a98795_7.0","SEXNUM_":2,"G_SEXNUM":2,"CITYCODE_":11,"G_CITYCODE":11,"AGECODE_":15,"G_AGECODE":15,"G_BLOODSUGAR_AVG":104.66666666666667,"G_BLOODSUGAR_DSTD":1.5275252316519465,"G_SBP_AVG":133.0,"G_SBP_DSTD":16.522711641858304,"G_DBP_AVG":74.0,"G_DBP_DSTD":13.076696830622021,"G_DRINK_CNCT":"0/1/1","G_DRINK_DMX":1,"G_CIGAR_CNCT":"1/1/1","G_CIGAR_DMX":1,"G_SEX_CNCT":"female/female/female","G_SEX_DMX":"female","GID_INDEX":"b0674834872f6f7d7eeb893852a98795_7.0"}
{"window":{"start":"2019-05-03T07:17:40.000+09:00","end":"2019-05-03T07:17:45.000+09:00"},"GID_INDEX":"baa939301bcf5d75dbf93f30f7b246d8_7.0","SEXNUM_":1,"G_SEXNUM":1,"CITYCODE_":41,"G_CITYCODE":41,"AGECODE_":8,"G_AGECODE":8,"G_BLOODSUGAR_AVG":91.66666666666667,"G_BLOODSUGAR_DSTD":0.5773502691896257,"G_SBP_AVG":119.0,"G_SBP_DSTD":1.7320508075688772,"G_DBP_AVG":72.66666666666667,"G_DBP_DSTD":11.015141094572204,"G_DRINK_CNCT":"1/0/0","G_DRINK_DMX":1,"G_CIGAR_CNCT":"1/3/1","G_CIGAR_DMX":3,"G_SEX_CNCT":"male/male/male","G_SEX_DMX":"male","GID_INDEX":"baa939301bcf5d75dbf93f30f7b246d8_7.0"}
{"window":{"start":"2019-05-03T07:17:40.000+09:00","end":"2019-05-03T07:17:45.000+09:00"},"GID_INDEX":"f67e28f99c036eed08ac2d7862f8f736_3.0","SEXNUM_":1,"G_SEXNUM":1,"CITYCODE_":31,"G_CITYCODE":31,"AGECODE_":7,"G_AGECODE":7,"G_BLOODSUGAR_AVG":102.0,"G_BLOODSUGAR_DSTD":4.58257569495584,"G_SBP_AVG":120.66666666666667,"G_SBP_DSTD":5.131601439446884,"G_DBP_AVG":74.66666666666667,"G_DBP_DSTD":8.082903768654761,"G_DRINK_CNCT":"0/0/1","G_DRINK_DMX":1,"G_CIGAR_CNCT":"2/3/3","G_CIGAR_DMX":3,"G_SEX_CNCT":"male/male/male","G_SEX_DMX":"male","GID_INDEX":"f67e28f99c036eed08ac2d7862f8f736_3.0"}
{"window":{"start":"2019-05-03T07:17:40.000+09:00","end":"2019-05-03T07:17:45.000+09:00"},"GID_INDEX":"0d53dd0e743b2172896b2519eba3ef70_4.0","SEXNUM_":1,"G_SEXNUM":1,"CITYCODE_":28,"G_CITYCODE":28,"AGECODE_":12,"G_AGECODE":12,"G_BLOODSUGAR_AVG":95.33333333333333,"G_BLOODSUGAR_DSTD":0.5773502691896257,"G_SBP_AVG":132.66666666666666,"G_SBP_DSTD":4.618802153517006,"G_DBP_AVG":81.66666666666667,"G_DBP_DSTD":2.886751345948129,"G_DRINK_CNCT":"0/0/0","G_DRINK_DMX":0,"G_CIGAR_CNCT":"2/3/1","G_CIGAR_DMX":3,"G_SEX_CNCT":"male/male/male","G_SEX_DMX":"male","GID_INDEX":"0d53dd0e743b2172896b2519eba3ef70_4.0"}
{"window":{"start":"2019-05-03T07:17:40.000+09:00","end":"2019-05-03T07:17:45.000+09:00"},"GID_INDEX":"4a86f434aa742e3e2d42b4811e816714_2.0","SEXNUM_":1,"G_SEXNUM":1,"CITYCODE_":47,"G_CITYCODE":47,"AGECODE_":8,"G_AGECODE":8,"G_BLOODSUGAR_AVG":88.0,"G_BLOODSUGAR_DSTD":2.6457513110645907,"G_SBP_AVG":115.66666666666667,"G_SBP_DSTD":14.364307617610162,"G_DBP_AVG":74.66666666666667,"G_DBP_DSTD":12.662279942148386,"G_DRINK_CNCT":"0/1/1","G_DRINK_DMX":1,"G_CIGAR_CNCT":"2/1/1","G_CIGAR_DMX":2,"G_SEX_CNCT":"male/male/male","G_SEX_DMX":"male","GID_INDEX":"4a86f434aa742e3e2d42b4811e816714_2.0"}
{"window":{"start":"2019-05-03T07:17:40.000+09:00","end":"2019-05-03T07:17:45.000+09:00"},"GID_INDEX":"3fe833700922f86b4cc7f86af7413b67_9.0","SEXNUM_":1,"G_SEXNUM":1,"CITYCODE_":11,"G_CITYCODE":11,"AGECODE_":10,"G_AGECODE":10,"G_BLOODSUGAR_AVG":98.0,"G_BLOODSUGAR_DSTD":1.0,"G_SBP_AVG":112.66666666666667,"G_SBP_DSTD":8.32666399786453,"G_DBP_AVG":72.33333333333333,"G_DBP_DSTD":4.041451884327381,"G_DRINK_CNCT":"1/0/1","G_DRINK_DMX":1,"G_CIGAR_CNCT":"3/2/3","G_CIGAR_DMX":3,"G_SEX_CNCT":"male/male/male","G_SEX_DMX":"male","GID_INDEX":"3fe833700922f86b4cc7f86af7413b67_9.0"}
{"window":{"start":"2019-05-03T07:17:40.000+09:00","end":"2019-05-03T07:17:45.000+09:00"},"GID_INDEX":"3fc73b5b666b5eee1ff4ba2d9922a312_12.0","SEXNUM_":2,"G_SEXNUM":2,"CITYCODE_":28,"G_CITYCODE":28,"AGECODE_":9,"G_AGECODE":9,"G_BLOODSUGAR_AVG":113.66666666666667,"G_BLOODSUGAR_DSTD":1.5275252316519465,"G_SBP_AVG":117.0,"G_SBP_DSTD":12.767145334803704,"G_DBP_AVG":74.66666666666667,"G_DBP_DSTD":11.015141094572204,"G_DRINK_CNCT":"0/0/0","G_DRINK_DMX":0,"G_CIGAR_CNCT":"1/1/1","G_CIGAR_DMX":1,"G_SEX_CNCT":"female/female/female","G_SEX_DMX":"female","GID_INDEX":"3fc73b5b666b5eee1ff4ba2d9922a312_12.0"}
{"window":{"start":"2019-05-03T07:17:40.000+09:00","end":"2019-05-03T07:17:45.000+09:00"},"GID_INDEX":"1da83df23fb6f140ae291c25478005b1_16.0","SEXNUM_":1,"G_SEXNUM":1,"CITYCODE_":41,"G_CITYCODE":41,"AGECODE_":9,"G_AGECODE":9,"G_BLOODSUGAR_AVG":94.0,"G_BLOODSUGAR_DSTD":0.0,"G_SBP_AVG":116.0,"G_SBP_DSTD":3.605551275463989,"G_DBP_AVG":81.0,"G_DBP_DSTD":7.937253933193772,"G_DRINK_CNCT":"0/1/0","G_DRINK_DMX":1,"G_CIGAR_CNCT":"3/1/3","G_CIGAR_DMX":3,"G_SEX_CNCT":"male/male/male","G_SEX_DMX":"male","GID_INDEX":"1da83df23fb6f140ae291c25478005b1_16.0"}
